mga/__init__.py
mga/mga_demuxer_main.py
mga/mga_file.py
mga/mga_muxer_main.py
sadm2wav/__init__.py
sadm2wav/sadm2wav_main.py
sadm_analyzer/__init__.py
sadm_analyzer/sadm_analyzer_main.py
sadm_tools-1.1.1.dist-info/METADATA
sadm_tools-1.1.1.dist-info/WHEEL
sadm_tools-1.1.1.dist-info/entry_points.txt
sadm_tools-1.1.1.dist-info/top_level.txt
sadm_tools-1.1.1.dist-info/RECORD
