Metadata-Version: 2.4
Name: sadm-tools
Version: 1.1.1
Summary: A collection of tools useful for dealing with Serialized ADM as specified in Recommendation ITU-R BS.2125, ST 2116, ST 2127-2
Author-email: James Cowdery <jtc@dolby.com>
Classifier: Programming Language :: Python :: 3
Classifier: Operating System :: OS Independent
Requires-Python: >=3
Requires-Dist: numpy>=1.24.4
Requires-Dist: soundfile>=0.12.1
